plank/decorator/fastapi.py
plank/descriptor/fastapi.py
plank/server/fastapi/__init__.py
plank/server/fastapi/action.py
plank/server/fastapi/interface.py
plank/support/__init__.py
plank/support/fastapi/__init__.py
plank/support/fastapi/builtin.py
plank/support/fastapi/settings.py
plank/support/fastapi/swagger.py
plank_extend_fastapi-0.1.0.dist-info/WHEEL
plank_extend_fastapi-0.1.0.dist-info/METADATA
plank_extend_fastapi-0.1.0.dist-info/RECORD
