Metadata-Version: 2.1
Name: plank-extend-fastapi
Version: 0.1.0
Summary: 
Author: Grady Zhuo
Author-email: grady@ospark.org
Requires-Python: >=3.8,<4.0
Classifier: Programming Language :: Python :: 3
Classifier: Programming Language :: Python :: 3.8
Classifier: Programming Language :: Python :: 3.9
Classifier: Programming Language :: Python :: 3.10
Classifier: Programming Language :: Python :: 3.11
Requires-Dist: fastapi (>=0.78.0,<0.79.0)
Requires-Dist: plank (>=0.1.0,<0.2.0)
Requires-Dist: pydantic (>=1.9.2,<2.0.0)
Requires-Dist: uvicorn (>=0.17.6,<0.18.0)
